{"albumId":14,"collectionId":null,"totalDurationMs":4309078,"trackCount":8,"tracks":[{"number":1,"name":"[Vaka]","artist":"Sigur Rós","durationMs":398320,"featuring":null,"previewUrl":null},{"number":2,"name":"[Fyrsta]","artist":"Sigur Rós","durationMs":453813,"featuring":null,"previewUrl":null},{"number":3,"name":"[Samskeyti]","artist":"Sigur Rós","durationMs":393426,"featuring":null,"previewUrl":null},{"number":4,"name":"[Njósnavélin]","artist":"Sigur Rós","durationMs":452960,"featuring":null,"previewUrl":null},{"number":5,"name":"[Álafoss]","artist":"Sigur Rós","durationMs":597026,"featuring":null,"previewUrl":null},{"number":6,"name":"[E‐Bow]","artist":"Sigur Rós","durationMs":528520,"featuring":null,"previewUrl":null},{"number":7,"name":"[Dauðalagið]","artist":"Sigur Rós","durationMs":779920,"featuring":null,"previewUrl":null},{"number":8,"name":"[Popplagið]","artist":"Sigur Rós","durationMs":705093,"featuring":null,"previewUrl":null}],"cached":false}